rnbrw/__init__.py
rnbrw/utils.py
rnbrw/community/__init__.py
rnbrw/community/louvain.py
rnbrw/weights/__init__.py
rnbrw/weights/rnbrw.py
rnbrw-0.1.7.2.dist-info/LICENSE
rnbrw-0.1.7.2.dist-info/METADATA
rnbrw-0.1.7.2.dist-info/WHEEL
rnbrw-0.1.7.2.dist-info/top_level.txt
rnbrw-0.1.7.2.dist-info/RECORD
