Metadata-Version: 2.1
Name: rnbrw
Version: 0.1.7.2
Summary: Renewal Non-Backtracking Random Walk (RNBRW) for scalable community detection
Home-page: https://github.com/lBehnaz-m/RNBRW/
Author: Behnaz Moradi-Jamei
Author-email: your_email@domain.com
Classifier: Programming Language :: Python :: 3
Classifier: License :: OSI Approved :: MIT License
Classifier: Operating System :: OS Independent
Requires-Python: >=3.7
License-File: LICENSE
Requires-Dist: numpy >=1.20
Requires-Dist: scipy
Requires-Dist: matplotlib
Requires-Dist: networkx >=2.6
Requires-Dist: joblib
Requires-Dist: python-louvain
